hyperdrivetypes/__init__.py
hyperdrivetypes/fixedpoint_types.py
hyperdrivetypes/types/__init__.py
hyperdrivetypes/types/pypechain.version
hyperdrivetypes/types/AaveBase/AaveBaseContract.py
hyperdrivetypes/types/AaveBase/AaveBaseTypes.py
hyperdrivetypes/types/AaveBase/__init__.py
hyperdrivetypes/types/AaveConversions/__init__.py
hyperdrivetypes/types/AaveHyperdrive/AaveHyperdriveContract.py
hyperdrivetypes/types/AaveHyperdrive/AaveHyperdriveTypes.py
hyperdrivetypes/types/AaveHyperdrive/__init__.py
hyperdrivetypes/types/AaveHyperdriveCoreDeployer/AaveHyperdriveCoreDeployerContract.py
hyperdrivetypes/types/AaveHyperdriveCoreDeployer/__init__.py
hyperdrivetypes/types/AaveHyperdriveDeployerCoordinator/AaveHyperdriveDeployerCoordinatorContract.py
hyperdrivetypes/types/AaveHyperdriveDeployerCoordinator/__init__.py
hyperdrivetypes/types/AaveHyperdriveTest/AaveHyperdriveTestContract.py
hyperdrivetypes/types/AaveHyperdriveTest/AaveHyperdriveTestTypes.py
hyperdrivetypes/types/AaveHyperdriveTest/__init__.py
hyperdrivetypes/types/AaveL2Base/AaveL2BaseContract.py
hyperdrivetypes/types/AaveL2Base/AaveL2BaseTypes.py
hyperdrivetypes/types/AaveL2Base/__init__.py
hyperdrivetypes/types/AaveL2Conversions/__init__.py
hyperdrivetypes/types/AaveL2Hyperdrive/AaveL2HyperdriveContract.py
hyperdrivetypes/types/AaveL2Hyperdrive/AaveL2HyperdriveTypes.py
hyperdrivetypes/types/AaveL2Hyperdrive/__init__.py
hyperdrivetypes/types/AaveL2HyperdriveCoreDeployer/AaveL2HyperdriveCoreDeployerContract.py
hyperdrivetypes/types/AaveL2HyperdriveCoreDeployer/__init__.py
hyperdrivetypes/types/AaveL2HyperdriveDeployerCoordinator/AaveL2HyperdriveDeployerCoordinatorContract.py
hyperdrivetypes/types/AaveL2HyperdriveDeployerCoordinator/__init__.py
hyperdrivetypes/types/AaveL2HyperdriveTest/AaveL2HyperdriveTestContract.py
hyperdrivetypes/types/AaveL2HyperdriveTest/AaveL2HyperdriveTestTypes.py
hyperdrivetypes/types/AaveL2HyperdriveTest/__init__.py
hyperdrivetypes/types/AaveL2Target0/AaveL2Target0Contract.py
hyperdrivetypes-1.0.20.13.dist-info/WHEEL
hyperdrivetypes-1.0.20.13.dist-info/METADATA
hyperdrivetypes-1.0.20.13.dist-info/RECORD
